[{"_id": 99202379, "propertyCode": "99202379", "thumbnail": "https://img3.idealista.com/blur/WEB_LISTING/0/id.pro.es.image.master/5e/70/cf/1036488853.jpg", "numPhotos": 18, "floor": "4", "price": 148000.0, "propertyType": "flat", "operation": "sale", "size": 111.0, "exterior": true, "rooms": 3, "bathrooms": 2, "address": "Calle Pelota, 12", "province": "Val\u00e8ncia", "municipality": "Benim\u00e0met", "country": "es", "latitude": 39.4977613, "longitude": -0.4175071, "showAddress": true, "url": "https://www.idealista.com/inmueble/99202379/", "description": "Ponemos a la venta este excepcional piso, completamente reformado, con much\u00edsima luz y ventilaci\u00f3n ya que da totalmente exterior a dos calles, \u00faltima planta de una finca tranquila de 4 plantas con 1 piso por planta, muy c\u00f3modo para el acceso de la terraza superior para tender. El piso dispone de puerta blindada, entrada a la cocina y sal\u00f3n con un balc\u00f3n grande que da vistas a la entrada de Valencia por Cortes, despu\u00e9s pasamos a 3 amplias habitaciones, todas muy grandes con buena distribuci\u00f3n y dos ba\u00f1os, todo completamente reformado.  Listo para inversi\u00f3n de alquiler o para disfrutarlo desde ya.  No dudes en llamar o mandar un whatsapp al 623108363 para que enviemos el v\u00eddeo de presentaci\u00f3n y organizar una visita.", "hasVideo": false, "status": "good", "newDevelopment": false, "hasLift": false, "priceByArea": 1333.0, "detailedType": {"typology": "flat"}, "suggestedTexts": {"subtitle": "Benim\u00e0met", "title": "Piso en Calle Pelota, 12"}, "hasPlan": false, "has3DTour": false, "has360": false, "hasStaging": false, "topNewDevelopment": false, "superTopHighlight": false, "date": "2022-10-18"}, {"_id": 100002920, "propertyCode": "100002920", "thumbnail": "https://img3.idealista.com/blur/WEB_LISTING/90/id.pro.es.image.master/74/17/2d/1066117420.jpg", "externalReference": "PAT-22023", "numPhotos": 30, "floor": "4", "price": 410000.0, "propertyType": "penthouse", "operation": "sale", "size": 146.0, "exterior": true, "rooms": 2, "bathrooms": 2, "address": "Porvenir", "province": "Val\u00e8ncia", "municipality": "Val\u00e8ncia", "district": "Quatre Carreres", "country": "es", "neighborhood": "En Corts", "latitude": 39.4548722, "longitude": -0.3731492, "showAddress": false, "url": "https://www.idealista.com/inmueble/100002920/", "description": "\u00bfBuscas un \u00e1tico con encanto a pocos minutos del centro de Valencia, en el barrio de Ruzafa? Inmobiliaria Patacona te presenta en exclusiva esta maravilla de \u00e1tico con una fant\u00e1stica terraza.  Gracias a su magn\u00edfica distribuci\u00f3n te enamoraras nada m\u00e1s entrar por la puerta, pr\u00e1cticamente desde cualquier punto de esta joya est\u00e1s viendo la terraza y la luz que se filtra a todos los rincones de esta maravillosa propiedad.  Accedemos a la vivienda por un recibidor que da acceso inmediato al sal\u00f3n comedor que con un gran ventanal que no sabes si est\u00e1s fuera o dentro de la terraza, donde empezamos a ver la luz que entra por todos lados. En esta planta accedemos a una amplia cocina, un ba\u00f1o y el dormitorio principal y se accede directamente al alma de la casa, una gran terraza donde podemos disfrutar durante todo el a\u00f1o. Desde su acogedor sal\u00f3n accedemos mediante unas escaleras a una buhardilla de 70 metros cuadrados aproximados, donde disponemos de una zona de estudio, un dormitorio y un ba\u00f1o. Tiene la posibilidad de poder hacer dos dormitorios con ba\u00f1o, si lo que se desea es disponer de tres dormitorios independientes. El encanto del piso con acabados de gama alta y la iluminaci\u00f3n indirecta hacen de esta propiedad una aut\u00e9ntica joya para los amantes del buen gusto que quieran una vivienda con terraza en uno de los barrios m\u00e1s de moda de Valencia.  Est\u00e1 equipada con aire acondicionado fr\u00edo y calor y carpinter\u00eda exterior climalit.  En resumen, algo \u00fanico ahora mismo en venta en Valencia con 40 metros cuadrados de terraza de la que disfrutar los 365 d\u00edas del a\u00f1o.  Ll\u00e1menos y estaremos encantados de poder atenderle.", "hasVideo": false, "status": "good", "newDevelopment": false, "hasLift": true, "priceByArea": 2808.0, "detailedType": {"typology": "flat", "subTypology": "penthouse"}, "suggestedTexts": {"subtitle": "En Corts, Val\u00e8ncia", "title": "\u00c1tico en Porvenir"}, "hasPlan": true, "has3DTour": true, "has360": false, "hasStaging": false, "topNewDevelopment": false, "superTopHighlight": false, "date": "2023-01-04"}, {"_id": 101898469, "propertyCode": "101898469", "thumbnail": "https://img3.idealista.com/blur/WEB_LISTING/0/id.pro.es.image.master/7c/c3/29/1145111619.jpg", "externalReference": "64-02480", "numPhotos": 46, "floor": "3", "price": 210000.0, "propertyType": "penthouse", "operation": "sale", "size": 115.0, "exterior": true, "rooms": 3, "bathrooms": 3, "address": "Calle Mestre Serrano", "province": "Val\u00e8ncia", "municipality": "Massalfassar", "country": "es", "latitude": 39.5550001, "longitude": -0.3256613, "showAddress": false, "url": "https://www.idealista.com/inmueble/101898469/", "description": "Estupendo \u00c1tico-Triplex, en residencial Lliri-Blau, de 115m2 + 2 terrazas de 25 metros cada una.  La Planta principal consta de amplio sal\u00f3n-comedor, cocina independiente totalmente equipada, aseo de cortesia y escaleras de acceso al resto de la vivienda.   La Planta inferior dispone de 3 habitaciones dobles con armarios empotrados y dos ba\u00f1os completos con ba\u00f1era (1 en suite).  En la Planta superior nos encontramos con una zona abuhardillada que nos sirve como zona de estar o despacho y nos da acceso a las 2 terrazas. Una est\u00e1 orientada al Sur y destinada a solarium y la otra tiene orientaci\u00f3n Norte y est\u00e1 techada con P\u00e9rgola de madera, zona de fregadero y barbacoa.  La vivienda est\u00e1 en perfecto estado para entrar a vivir y se le han ido haciendo mejoras con el tiempo.  Dispone de Placas solares para agua caliente; Dom\u00f3tica; Climalit y sistema natural de ventilaci\u00f3n cruzada.  Garaje y trastero incluidos en el precio.  El residencial cuenta con Gimnasio, Zona verde, piscina climatizada y servicio de conserjer\u00eda.  Zona Blasco Iba\u00f1ez - Urb. Lliri Blau, a 100 metros del centro del pueblo y del Polideportivo.    Massalfassar cuenta con todo tipo de servicios y comercios, como farmacia, centro de salud, cafeterias, Centro C\u00edvico, Parques infantiles, supermercados y a un paso del C. C. El Manar y de la Playa.  Tren de cercan\u00edas a 8 min. andando y con facil acceso a la autov\u00eda.    La vivienda se vende sin muebles  Gastos compraventa no incluidos (Notar\u00eda, Registro, Impuestos y Honorarios Agencia). Este anuncio no es vinculante y puede contener errores, se muestra a t\u00edtulo informativo y no contractual.", "hasVideo": false, "status": "good", "newDevelopment": false, "hasLift": true, "parkingSpace": {"hasParkingSpace": true, "isParkingSpaceIncludedInPrice": true}, "priceByArea": 1826.0, "detailedType": {"typology": "flat", "subTypology": "penthouse"}, "suggestedTexts": {"subtitle": "Massalfassar", "title": "\u00c1tico en Calle Mestre Serrano"}, "hasPlan": true, "has3DTour": false, "has360": true, "hasStaging": false, "highlight": {"groupDescription": "Destacado"}, "superTopHighlight": false, "topNewDevelopment": false, "date": "2023-07-30"}, {"_id": 98415055, "propertyCode": "98415055", "externalReference": "1000037205-CV", "numPhotos": 0, "price": 37800.0, "propertyType": "flat", "operation": "sale", "size": 121.0, "exterior": false, "rooms": 3, "bathrooms": 2, "address": "Calle Mare de D\u00e9u del Pilar", "province": "Val\u00e8ncia", "municipality": "Quart de Poblet", "country": "es", "latitude": 39.4825457, "longitude": -0.4413591, "showAddress": false, "url": "https://www.idealista.com/inmueble/98415055/", "description": "Vivienda-piso.", "hasVideo": false, "status": "good", "newDevelopment": false, "hasLift": false, "priceByArea": 312.0, "detailedType": {"typology": "flat"}, "suggestedTexts": {"subtitle": "Quart de Poblet", "title": "Piso en Calle Mare de D\u00e9u del Pilar"}, "hasPlan": false, "has3DTour": false, "has360": false, "hasStaging": false, "superTopHighlight": false, "topNewDevelopment": false, "date": "2022-12-15"}, {"_id": 102075012, "propertyCode": "102075012", "thumbnail": "https://img3.idealista.com/blur/WEB_LISTING/0/id.pro.es.image.master/5e/77/08/1143397296.jpg", "externalReference": "015HAMAJ130", "numPhotos": 38, "floor": "5", "price": 129900.0, "propertyType": "penthouse", "operation": "sale", "size": 77.0, "exterior": true, "rooms": 2, "bathrooms": 2, "address": "Calle Mestra D\u00aa Juana", "province": "Val\u00e8ncia", "municipality": "Paiporta", "country": "es", "latitude": 39.4300609, "longitude": -0.4164299, "showAddress": false, "url": "https://www.idealista.com/inmueble/102075012/", "description": "015HAMAJ130. \u00c1TICO REFORMADO A ESTRENAR DEL QUE TE ENAMORAR\u00c1S A PRIMERA VISTA Financiaci\u00f3n hasta 100% (sujeto a aprobaci\u00f3n por entidades bancarias) Este \u00e1tico reformado a estrenar te conquistar\u00e1 desde el primer momento que pongas un pie en \u00e9l. Con un dise\u00f1o moderno y elegante, cada detalle ha sido cuidadosamente pensado para brindarte el m\u00e1ximo confort y bienestar. Distribuido en 2 dormitorios dobles, 2 ba\u00f1os completos y una cocina americana totalmente equipada. El espacioso sal\u00f3n-comedor tiene acceso directo a una encantadora terraza. Instalaciones de electricidad y fontaner\u00eda totalmente nuevas. Excelentes calidades, cuenta con armarios empotrados, ventanas de PVC-climalit, puertas de madera lacada en blanco, suelo de gres porcel\u00e1nico y puerta blindada. Edificio sin ascensor, a 3 minutos a pie del Ayuntamiento y Auditori Municipal de Paiporta, 7 minutos del metro, 10 minutos en coche a Valencia. No pierdas esta oportunidad de vivir en un \u00e1tico de ensue\u00f1o. \u00a1Ll\u00e1manos para recibir m\u00e1s informaci\u00f3n! Ofrecemos varias opciones de visitas a distancia, cons\u00faltanos. Destinamos el 3% de beneficio a ONG's y acci\u00f3n social \u00bfVendes tu casa? TE ADELANTAMOS EL DINERO que necesites y devu\u00e9lvelo a la venta \u00a1SIN INTERESES!* Tambi\u00e9n REFORMAMOS, PINTAMOS, AMUEBLAMOS Y DECORAMOS GRATIS para que VENDAS MEJOR Y M\u00c1S R\u00c1PIDO* (sujeto a aprobaci\u00f3n)  Este anuncio es informativo y sin valor contractual, puede contener errores. Gastos e impuestos no incluidos. ABIERTO A MEDIOD\u00cdA. Oficinas en Valencia/Gand\u00eda/Castell\u00f3n. CONSENTIMIENTO PARA EL TRATAMIENTO DE DATOS PERSONALES. Para continuar debe aceptar que ha le\u00eddo y est\u00e1 conforme con las cl\u00e1usulas siguientes, entendiendo que el env\u00edo de sus datos tanto mediante email como mediante el formulario de contacto de esta web supone el consentimiento expl\u00edcito para el tratamiento de los mismos en los t\u00e9rminos y condiciones aqu\u00ed expuestos as\u00ed como en nuestra pol\u00edtica de privacidad y aviso legal. Acuda a nuestra web para el texto \u00edntegro en caso de error. HOGARABITAT SERVICIOS INMOBILIARIOS S.L. es el Responsable del tratamiento de los datos personales del Usuario y le informa que estos datos ser\u00e1n tratados de conformidad con lo dispuesto en el Reglamento (UE) 2016/679 de 27 de abril de 2016 (GDPR) y la Ley Org\u00e1nica 3/2018 de 5 de diciembre (LOPDGDD), por lo que se le facilita la siguiente informaci\u00f3n del tratamiento: Fin del tratamiento: mantener una relaci\u00f3n comercial y el env\u00edo de comunicaciones y/o publicidad sobre nuestros productos y servicios. Criterios de conservaci\u00f3n de los datos: se conservar\u00e1n mientras exista un inter\u00e9s mutuo para mantener el fin del tratamiento y cuando ya no sea necesario para tal fin, se suprimir\u00e1n con medidas de seguridad adecuadas para garantizar la seudonimizaci\u00f3n de los datos o la destrucci\u00f3n total de los mismos. No se comunicar\u00e1n los datos a terceros, salvo obligaci\u00f3n legal. Derechos que asisten al Usuario: - A retirar el consentimiento en cualquier momento. - De acceso, rectificaci\u00f3n, portabilidad y supresi\u00f3n de sus datos y a la limitaci\u00f3n u oposici\u00f3n a su tratamiento. - A presentar una reclamaci\u00f3n ante la Autoridad de control (agpd.es) si considera que el tratamiento no se ajusta a la normativa vigente. Datos de contacto para ejercer sus derechos: HOGARABITAT SERVICIOS INMOBILIARIOS S.L. AV. P\u00c9REZ GALDOS, 42 46008 VALENCIA. Email:  We speak English Nous parlons Fran\u00e7ais \u041c\u044b \u0433\u043e\u0432\u043e\u0440\u0438\u043c \u043d\u0430 \u0440\u0443\u0441\u0441\u043a\u043e\u043c Wij spreken Nederlands \u6211\u4eec\u63d0\u4f9b\u4e2d\u6587\u670d\u52a1\u3002  \u0646\u062a\u0643\u0644\u0645 \u0627\u0644\u0639\u0631\u0628\u064a\u0629 Amplia gama de servicios: Compraventa, Alquiler, Financiaci\u00f3n, Certificados de Eficiencia Energ\u00e9tica, Herencias y Donaciones, Gestor\u00eda, Capitales Privados, Inversores, Cancelaci\u00f3n de Embargos, etc.", "hasVideo": true, "status": "good", "newDevelopment": false, "hasLift": false, "priceByArea": 1687.0, "detailedType": {"typology": "flat", "subTypology": "penthouse"}, "suggestedTexts": {"subtitle": "Paiporta", "title": "\u00c1tico en Calle Mestra D\u00aa Juana"}, "hasPlan": true, "has3DTour": false, "has360": false, "hasStaging": false, "highlight": {"groupDescription": "Destacado"}, "superTopHighlight": false, "topNewDevelopment": false, "date": "2023-07-31"}, {"_id": 98992130, "propertyCode": "98992130", "thumbnail": "https://img3.idealista.com/blur/WEB_LISTING/0/id.pro.es.image.master/2f/f0/5d/1030719843.jpg", "externalReference": "SBRE-0127896", "numPhotos": 50, "floor": "2", "price": 78000.0, "propertyType": "duplex", "operation": "sale", "size": 134.0, "exterior": true, "rooms": 3, "bathrooms": 2, "address": "Calle Comtat", "province": "Val\u00e8ncia", "municipality": "Villalonga", "country": "es", "latitude": 38.8843, "longitude": -0.21313, "showAddress": false, "url": "https://www.idealista.com/inmueble/98992130/", "description": "Piso d\u00faplex de tres dormitorios, dos ba\u00f1os, un aseo y amplias terrazas ubicado en la planta segunda de un edificio de cuatro alturas sobre rasante con ascensor. Se encuentra ubicado Villalonga, municipio de la Comunidad Valenciana, Espa\u00f1a. Pertenece a la provincia de Valencia, en la comarca de Safor.    Vivienda de dos plantas con terraza en la azotea. La planta baja se distribuye en hall, tres dormitorios, un ba\u00f1o, un aseo y balc\u00f3n. La planta primera de compone de sal\u00f3n-comedor, un ba\u00f1o, cocina independiente y balc\u00f3n. En la azotea se encuentra una terraza.  La transmisi\u00f3n de la vivienda, comporta obligatoriamente la adquisici\u00f3n de garaje, no pudi\u00e9ndose adquirir de forma individual, a no ser que hayan sobrantes.    La vivienda cuenta con puertas interiores de madera, armarios emportrados, ventanas correderas de aluminio adonizado lacado en blanco y suelos de plaqueta. El ba\u00f1o principal cuenta con ba\u00f1era de chapa esmaltada y el aseo con ducha. La cocina esta equipada con muebles altos y bajos y cuenta con vitro-cer\u00e1mica, horno empotrado el\u00e9ctrico y campana extractora. Banca de granito. Dispone de preinstalaci\u00f3n de aire acondicionado, termo el\u00e9ctrico y portero electr\u00f3nico.    Edificio de cuatro plantas sobre rasante y una bajo rasante. Su a\u00f1o de construcci\u00f3n es 2010 y se encuentra situado a cinco a pie del centro del municipio y a media hora en coche de la playa. El t\u00e9rmino municipal de Villalonga limita con las siguientes localidades: Ador, Castellonet, Fuente Encarroz, Lugar Nuevo de San Jer\u00f3nimo, Oliva, Potr\u00edes y Terrateig de la provincia de Valencia; Adsubia, Lorcha y Vall de Gallinera de la provincia de Alicante. En Villalonga destaca la Ermita de S. Antonio y Santa B\u00e1rbara (en la monta\u00f1a del calvario).    Zona con f\u00e1cil acceso por carretera (CV-685, AP-7 Y CV-60). Dispone de l\u00edneas de autobuses (Autob\u00fas Gand\u00eda-Villalonga). Cuenta con centros educativos, escuelas infantiles (Nadal Ripoll), colegios p\u00fablicos (Colegio P\u00fablico Verg\u00e9 de la Font. ) e institutos de educaci\u00f3n secundaria (IES Val de la Safor), centros sanitarios (Centro de Salud de Villalonga y David Marcos Fisioterapia y Osteopat\u00eda), supermercados (Mercadona) y hoteles (Casa Babel).", "hasVideo": false, "status": "good", "newDevelopment": false, "hasLift": true, "priceByArea": 582.0, "detailedType": {"typology": "flat", "subTypology": "duplex"}, "suggestedTexts": {"subtitle": "Villalonga", "title": "D\u00faplex en Calle Comtat"}, "hasPlan": true, "has3DTour": false, "has360": false, "hasStaging": false, "topNewDevelopment": false, "superTopHighlight": false, "date": "2022-10-03"}]